beniget/__init__.py
beniget/__main__.py
beniget/beniget.py
beniget/ordered_set.py
beniget/version.py
beniget-0.4.2.post1.dist-info/LICENSE
beniget-0.4.2.post1.dist-info/METADATA
beniget-0.4.2.post1.dist-info/WHEEL
beniget-0.4.2.post1.dist-info/top_level.txt
beniget-0.4.2.post1.dist-info/RECORD
